django_troop_auth/__init__.py
django_troop_auth/authentication.py
django_troop_auth/permission.py
django_troop_auth/user.py
django_troop_auth-0.1.0.dist-info/METADATA
django_troop_auth-0.1.0.dist-info/WHEEL
django_troop_auth-0.1.0.dist-info/top_level.txt
django_troop_auth-0.1.0.dist-info/RECORD
