Metadata-Version: 2.1
Name: django-troop-auth
Version: 0.1.0
Summary: UNKNOWN
Home-page: https://github.com/troopstack/django-troop-auth.git
License: UNKNOWN
Platform: UNKNOWN
Requires-Dist: django
Requires-Dist: djangorestframework
Requires-Dist: djangorestframework-jwt
Requires-Dist: django-json-rpc
